{
  "title": "Introduction to Bag of Words",
  "description": "Building Bag of Words model",
  "difficulty": "beginner",
  "time": "20 minutes",
  "details": {
    "steps": [
    {
      "title": "Read data",
      "text": "read_data.md"
    },
    {
      "title": "Tokenizing",
      "text": "tokenizing.md"
    },
    {
      "title": "Punctuation",
      "text": "punctuation.md"
    },
    {
      "title": "Stop words",
      "text": "stop_words.md"
    },
    {
      "title": "Words stemming",
      "text": "stemmer.md"
    },
    {
      "title": "Count vector",
      "text": "count_vector.md"
    }
    ],
    "intro": {
      "text": "intro.md",
      "credits": ""
    },
    "finish": {
      "text": "finish.md"
    },
    "assets": {
      "client": [{"file": "data_reader.py", "target": "~/"}]
    }
  },
  "environment": {
    "uilayout": "terminal",
    "uimessage1": "\u001b[32mYour Interactive Bash Terminal.\r\nStart using `python` command\u001b[m\r\n"
  },
  "backend": {
    "imageid": "python-nltk"
  }
}
